python_lib_test_lib/__init__.py
python_lib_test_lib-0.0.4.dist-info/LICENSE
python_lib_test_lib-0.0.4.dist-info/METADATA
python_lib_test_lib-0.0.4.dist-info/WHEEL
python_lib_test_lib-0.0.4.dist-info/entry_points.txt
python_lib_test_lib-0.0.4.dist-info/RECORD
