Metadata-Version: 2.1
Name: python-lib-test-lib
Version: 0.0.4
Summary: A test library to test the [python-lib](https://github.com/msleigh/python-lib) Cookiecutter template.
License: Apache-2.0
Author: msleigh
Author-email: msleigh@users.noreply.github.com
Requires-Python: >=3.11,<4.0
Classifier: License :: OSI Approved :: Apache Software License
Classifier: Programming Language :: Python :: 3
Classifier: Programming Language :: Python :: 3.11
Classifier: Programming Language :: Python :: 3.12
Provides-Extra: test
Requires-Dist: black (>=23.3.0,<24.0.0) ; extra == "test"
Requires-Dist: mkdocs-material (>=9.5.7,<10.0.0) ; extra == "test"
Requires-Dist: pre-commit (>=3.3.1,<4.0.0) ; extra == "test"
Requires-Dist: pytest (>=8.0.0,<9.0.0) ; extra == "test"
Requires-Dist: ruff (>=0.0.265,<0.0.266) ; extra == "test"
Requires-Dist: towncrier (>=23.11.0,<24.0.0) ; extra == "test"
